sockettools/__init__.py
sockettools/client.py
sockettools/clienthandler.py
sockettools/events.py
sockettools/protocol.py
sockettools/server.py
sockettools/transport.py
sockettools-1.0.1.dist-info/LICENCE.md
sockettools-1.0.1.dist-info/METADATA
sockettools-1.0.1.dist-info/WHEEL
sockettools-1.0.1.dist-info/top_level.txt
sockettools-1.0.1.dist-info/RECORD
