Metadata-Version: 2.1
Name: sockettools
Version: 1.0.1
Summary: Wrapper around built-in python sockets library
Author-email: Highghlow <highghlow@proton.me>
Project-URL: Homepage, https://github.com/highghlow/SocketTools
Project-URL: Bug Tracker, https://github.com/highghlow/SocketTools/issues
Classifier: Programming Language :: Python :: 3
Classifier: License :: OSI Approved :: MIT License
Classifier: Operating System :: OS Independent
Requires-Python: >=3.7
License-File: LICENCE.md
